dc_campaign_finance_scraper/__init__.py
dc_campaign_finance_scraper/cache.py
dc_campaign_finance_scraper/cli.py
dc_campaign_finance_scraper/scraper.py
dc_campaign_finance_scraper/tablib.py
dc_campaign_finance_scraper/utils.py
dc_campaign_finance_scrapers-0.5.1.data/scripts/dc-campaign-finance-scraper
dc_campaign_finance_scrapers-0.5.1.dist-info/DESCRIPTION.rst
dc_campaign_finance_scrapers-0.5.1.dist-info/entry_points.txt
dc_campaign_finance_scrapers-0.5.1.dist-info/METADATA
dc_campaign_finance_scrapers-0.5.1.dist-info/pydist.json
dc_campaign_finance_scrapers-0.5.1.dist-info/RECORD
dc_campaign_finance_scrapers-0.5.1.dist-info/top_level.txt
dc_campaign_finance_scrapers-0.5.1.dist-info/WHEEL
